{"name":"Phúc Bảo Ba Tuổi Rưỡi Được Tám Người Cậu Chiều Chuộng","folder":"phucbaobatuoiruoidjuoctamnguoicauchieuchuong","tacGia":"Mạnh Hàn Tử","theLoai":"Ngôn Tình","trangThai":"Đang ra","description":"\"Tiểu Tô Bảo\" kể về cô bé được coi là sao chổi và bị đuổi ra khỏi nhà sau mẹ kế của cô ngã cầu thang sảy thai. May mắn thay, tám người chú bạo chúa xuất hiện và giải cứu cô bé. Từ đó, cuộc sống của Tiểu Tô Bảo bắt đầu thay đổi từ bất hạnh sang may mắn khi cô trở về nhà họ Tô và được trở thành công chúa nhỏ với sự chiều chuộng của người bố tổng tài bá đạo.<br><br>Trong khi đó, \"Đứa con bất hạnh Tô Bảo\" xoay quanh nhân vật cùng tên cũng là một đứa trẻ bất hạnh của nhà họ Lâm. Sau khi bị mẹ kế hãm hại, cô đã qua đời nhưng được tám người chú cao lớn cứu giúp và mang đến cho cô một cuộc sống mới bên họ Tô. Tuy nhiên, cô vẫn phải đối mặt với những thử thách và những bí mật vô cùng nguy hiểm.<br><br>Cả hai tác phẩm đều có nội dung hài hước, huyền huyễn và ngôn tình, dễ đọc và phù hợp với độc giả muốn tìm kiếm một câu chuyện thú vị để giải trí.&nbsp;"}