{"name":"Chỉ Muốn Ngã Vào Lòng Anh","folder":"chimuonngavaolonganh","tacGia":"BaoTruc120","theLoai":"Ngôn Tình","trangThai":"Đang ra","description":"Bạn đang thưởng thức truyện \"Chỉ Muốn Ngã Vào Lòng Anh\" của tác giả BaoTruc120. Vì Thượng Quan Diên Dịch, Bối Quân Ninh đã không còn coi Bối Nguyệt Sương là người thân của mình nữa.<br><br>Vào mùa xuân năm đó, cô đã yêu anh nhưng bị từ chối. Trong khi đó, Nguyệt Sương chỉ đứng từ xa để nhìn anh.<br><br>Tuy nhiên, sau khi cha mẹ cô qua đời, cô không còn được tự do và lo sợ Bối Nguyệt Sương sẽ cướp mất anh. Vì vậy, cô bắt đầu kiểm soát cuộc sống của mình.<br><br>Bối Nguyệt Sương được cho là ngoan ngoãn nhưng thực sự cô mang giấc mơ công lý. Vào con đường biến giấc mơ thành hiện thực, cô gặp được Thượng Quan Diên Dịch.<br><br>Nếu bạn yêu thích truyện ngôn tình, bạn có thể đọc thêm \"Mặt Trăng Nhỏ Của Phó Dịch Bắc\" hoặc \"Cuộc Tình Này Dù Sao Cũng Chẳng Tồn Tại Được Lâu\"."}