{"name":"Xuyên Tới Nữ Tôn Nuôi Bốn Chồng","folder":"xuyentoinutonnuoibonchong","tacGia":"Lục Thiên Hoa","theLoai":"Ngôn Tình","trangThai":"Đang ra","description":"Đến với truyện Xuyên Tới Nữ Tôn Nuôi Bốn Chồng của tác giả Lục Thiên Hoa. Sau khi gặp tai nạn giao thông, Tống Kiều Thư bị xuyên không đến một thế giới nơi nữ giới bị khinh thường. Dù được sinh ra trong một gia đình giàu có, chủ nhân thể này lại là một lưu manh danh tiếng thối nát. Nhưng Tống Kiều Thư không để cho danh tiếng của mình bị phủ nhận. Cô nỗ lực làm việc để kiếm tiền, đưa tất cả mọi người qua những khó khăn. Bên cạnh đó, cô giúp đỡ các chàng trai xung quanh bằng những cách khác nhau.<br><br>Với lòng quyết tâm và sự cố gắng không ngừng, Tống Kiều Thư đã liệu pháp giải thoát được cả những cơn khủng hoảng của từng anh chàng. Hành Trình Theo Đuổi Lộc Y Ninh Của Cố Thiếu Gia hoặc Tiệm Bánh Đặc Biệt cũng là những tuyệt phẩm mà các bạn yêu thích thể loại ngôn tình không nên bỏ qua. <br><br>Bằng chữ tình yêu, các tác phẩm này sẽ mang đến cho bạn những cảm xúc tuyệt vời mà bạn chưa từng trải qua."}