{"name":"Sau Khi Nhà Giàu Tìm Ta Về","folder":"saukhinhagiautimtave","tacGia":"Tây Tích","theLoai":"Ngôn Tình","trangThai":"Đang ra","description":"Tây Tích - Lâm Khê là một nữ phi công giỏi trong quân đội, nhưng cô lại giả trai để gia nhập quân đội đao kiếm. Nhiều năm trôi qua với cuộc sống của một tiên phong binh, cho đến khi cô tìm thấy được người thân mà mình đã lạc trong một thời gian dài và trở thành một quý nữ của cao môn.<br><br>Cô tưởng rằng mình sẽ trở thành một cá mặn xoay người, nhưng thật không ngờ cô lại bị xuyên vào một cuốn tiểu thuyết Mary Sue rất cẩu huyết. Trong đó, nam chính tìm kiếm người đã cứu mạng mình và đến khi gặp nữ chính mới tỉnh ngộ. Tuy nhiên, nhờ đó cô nhận ra rằng mình đang vào vai giả trăng nữ, da mặt dày không muốn thoái vị.<br><br>Vì muốn tránh cốt truyện nguyên tác và cũng tiết kiệm tiền bớt việc, Lâm Khê quyết định lấy lui làm tiến để tìm một phu quân tốt. Nhưng điều đó không dễ dàng, vì cô đã tán tỉnh rất nhiều nam nhân xung quanh nữ chủ và hạt nhân Lục Diễm cũng đã giấu tài mấy năm để trở về giết ra một đường máu.<br><br>Trong khi đó, Tân Vương đã đăng cơ ba năm và Chu Vương cũng đang tu thư cho ông. Tuy nhiên, Lâm Khê lại muốn đe dọa Chu Vương để trở thành Vương hậu. Cuối cùng, cô nhận ra rằng mình đã làm những điều sai trái và quyết định thay đổi để làm một người tốt và sống chân thật hơn.<br><br>Câu chuyện này rất hấp dẫn và khiến người đọc tò mò và hồi hộp."}